Metadata-Version: 2.1
Name: django-simple-currencies-py3
Version: 1.0
Summary: Currency, exchange rate and conversions support for django projects
Home-page: https://github.com/ramananda-kairi/django-simple-currencies-py3
Author: Ramananda Kairi
Author-email: ramananda.kairi@gmail.com
License: BSD License
Platform: UNKNOWN
Classifier: Environment :: Web Environment
Classifier: Framework :: Django
Classifier: Intended Audience :: Developers
Classifier: License :: OSI Approved :: BSD License
Classifier: Operating System :: OS Independent
Classifier: Programming Language :: Python
Classifier: Topic :: Internet :: WWW/HTTP
Classifier: Topic :: Internet :: WWW/HTTP :: Dynamic Content
License-File: LICENSE
Requires-Dist: django-classy-tags
Requires-Dist: openexchangerates
